CHANGES
LICENSE
MANIFEST.in
README.rst
setup.py
.tox/docs/lib/python3.5/site-packages/dram/dram.sh
.tox/py27/lib/python2.7/site-packages/dram/dram.sh
.tox/py27/local/lib/python2.7/site-packages/dram/dram.sh
.tox/py35/lib/python3.5/site-packages/dram/dram.sh
docs/Makefile
docs/basics.rst
docs/conf.py
docs/contributing.rst
docs/hooks.rst
docs/index.rst
docs/_static/empty
dram/__init__.py
dram/dram.sh
dram.egg-info/PKG-INFO
dram.egg-info/SOURCES.txt
dram.egg-info/dependency_links.txt
dram.egg-info/entry_points.txt
dram.egg-info/not-zip-safe
dram.egg-info/requires.txt
dram.egg-info/top_level.txt