Metadata-Version: 1.1
Name: dram
Version: 0.0.4
Summary: Keeping your Package Manager Packaged
Home-page: https://github.com/storborg/dram
Author: Scott Torborg
Author-email: storborg@gmail.com
License: MIT
Keywords: shell macports homebrew software dependencies package manager
Platform: UNKNOWN
Classifier: Development Status :: 2 - Pre-Alpha
Classifier: License :: OSI Approved :: MIT License
